mcpproxy/__init__.py
mcpproxy/__main__.py
mcpproxy/logging.py
mcpproxy/indexer/__init__.py
mcpproxy/indexer/base.py
mcpproxy/indexer/bm25.py
mcpproxy/indexer/facade.py
mcpproxy/indexer/huggingface.py
mcpproxy/indexer/openai.py
mcpproxy/models/__init__.py
mcpproxy/models/schemas.py
mcpproxy/persistence/__init__.py
mcpproxy/persistence/bm25_store.py
mcpproxy/persistence/db.py
mcpproxy/persistence/facade.py
mcpproxy/persistence/faiss_store.py
mcpproxy/server/__init__.py
mcpproxy/server/config.py
mcpproxy/server/mcp_server.py
mcpproxy/utils/__init__.py
mcpproxy/utils/dependencies.py
mcpproxy/utils/hashing.py
smart_mcp_proxy-0.3.1.dist-info/METADATA
smart_mcp_proxy-0.3.1.dist-info/WHEEL
smart_mcp_proxy-0.3.1.dist-info/entry_points.txt
smart_mcp_proxy-0.3.1.dist-info/licenses/LICENSE
smart_mcp_proxy-0.3.1.dist-info/RECORD
