Metadata-Version: 2.4
Name: smart-mcp-proxy
Version: 0.3.1
Summary: Smart MCP Proxy - A federating gateway for MCP servers with intelligent tool discovery
Project-URL: Homepage, https://mcpproxy.app
Project-URL: Documentation, https://mcpproxy.app
Project-URL: Repository, https://github.com/Dumbris/mcpproxy
Project-URL: Bug Reports, https://github.com/Dumbris/mcpproxy/issues
Project-URL: Source Code, https://github.com/Dumbris/mcpproxy
Author-email: Algis Dumbris <a.dumbris@gmail.com>
Maintainer-email: Algis Dumbris <a.dumbris@gmail.com>
License: MIT
License-File: LICENSE
Keywords: ai,embedding,fastmcp,gateway,mcp,model-context-protocol,proxy,search,smart,tool-discovery
Classifier: Development Status :: 4 - Beta
Classifier: Intended Audience :: Developers
Classifier: License :: OSI Approved :: MIT License
Classifier: Operating System :: OS Independent
Classifier: Programming Language :: Python :: 3
Classifier: Programming Language :: Python :: 3.11
Classifier: Programming Language :: Python :: 3.12
Classifier: Topic :: Internet :: WWW/HTTP :: HTTP Servers
Classifier: Topic :: Scientific/Engineering :: Artificial Intelligence
Classifier: Topic :: Software Development :: Libraries :: Python Modules
Classifier: Topic :: System :: Distributed Computing
Requires-Python: >=3.11.1
Requires-Dist: bm25s>=0.2.13
Requires-Dist: fastmcp>=2.8.0
Requires-Dist: httpx>=0.28.1
Requires-Dist: numpy>=2.2.6
Requires-Dist: pydantic>=2.11.5
Provides-Extra: all
Requires-Dist: bm25s>=0.2.13; extra == 'all'
Requires-Dist: faiss-cpu>=1.11.0; extra == 'all'
Requires-Dist: openai>=1.86.0; extra == 'all'
Requires-Dist: sentence-transformers>=4.1.0; extra == 'all'
Provides-Extra: bm25
Requires-Dist: bm25s>=0.2.13; extra == 'bm25'
Provides-Extra: dev
Requires-Dist: build>=1.2.2.post1; extra == 'dev'
Requires-Dist: mypy>=1.9.0; extra == 'dev'
Requires-Dist: ruff>=0.8.0; extra == 'dev'
Provides-Extra: huggingface
Requires-Dist: bm25s>=0.2.13; extra == 'huggingface'
Requires-Dist: faiss-cpu>=1.11.0; extra == 'huggingface'
Requires-Dist: sentence-transformers>=4.1.0; extra == 'huggingface'
Provides-Extra: openai
Requires-Dist: bm25s>=0.2.13; extra == 'openai'
Requires-Dist: faiss-cpu>=1.11.0; extra == 'openai'
Requires-Dist: openai>=1.86.0; extra == 'openai'
Provides-Extra: test
Requires-Dist: pytest-asyncio>=1.0.0; extra == 'test'
Requires-Dist: pytest-cov>=4.0.0; extra == 'test'
Requires-Dist: pytest-mock>=3.10.0; extra == 'test'
Requires-Dist: pytest>=8.4.0; extra == 'test'
